<?xml version="1.0"?>

<translations>

	<translation>
		<nerd>Login</nerd>
		<ru><![CDATA[Логин]]></ru>
	</translation>

	<translation>
		<nerd>Logout</nerd>
		<ru><![CDATA[Выход]]></ru>
	</translation>

	<translation>
		<nerd>Members</nerd>
		<ru><![CDATA[Пользователи]]></ru>
	</translation>

	<translation>
		<nerd>Register</nerd>
		<ru><![CDATA[Регистрация]]></ru>
	</translation>

	<translation>
		<nerd>Photo gallery</nerd>
		<ru><![CDATA[Фотогалерея]]></ru>
	</translation>

	<translation>
		<nerd>Breadcrumbs: User's photos</nerd>
		<ru><![CDATA[Работы]]></ru>
	</translation>

	<translation>
		<nerd>All user's photos</nerd>
		<ru><![CDATA[Работы]]></ru>
	</translation>

	<translation>
		<nerd>My club</nerd>
		<ru><![CDATA[Мой клуб]]></ru>
	</translation>

	<translation>
		<nerd>My bookmarks</nerd>
		<ru><![CDATA[Мои закладки]]></ru>
	</translation>

	<translation>
		<nerd>My subscription</nerd>
		<ru><![CDATA[Мои подписки]]></ru>
	</translation>

	<translation>
		<nerd>Administration</nerd>
		<ru><![CDATA[Администрирование]]></ru>
	</translation>

	<translation>
		<nerd>Messages</nerd>
		<ru><![CDATA[Сообщения]]></ru>
	</translation>

	<translation>
		<nerd>Private Messages</nerd>
		<ru><![CDATA[Личные сообщения]]></ru>
	</translation>

	<translation>
		<nerd>Private Message</nerd>
		<ru><![CDATA[Личное сообщение]]></ru>
	</translation>

	<translation>
		<nerd>Access denied</nerd>
		<ru><![CDATA[Доступ закрыт]]></ru>
	</translation>

	<translation>
		<nerd>Post your soul here</nerd>
		<ru><![CDATA[Опубликуй мечту здесь]]></ru>
	</translation>

	<translation>
		<nerd>Sorted by</nerd>
		<ru><![CDATA[Отсортировано по]]></ru>
	</translation>

	<translation>
		<nerd>upload time descending</nerd>
		<ru><![CDATA[дате загрузки по убыванию]]></ru>
	</translation>

	<translation>
		<nerd>marks for period descending</nerd>
		<ru><![CDATA[оценкам за период по убыванию]]></ru>
	</translation>

	<translation>
		<nerd>Portal page</nerd>
		<ru><![CDATA[Главная страница]]></ru>
	</translation>

	<translation>
		<nerd>Top authors of the week</nerd>
		<ru><![CDATA[Лучшие авторы недели]]></ru>
	</translation>

	<translation>
		<nerd>Top authors of the month</nerd>
		<ru><![CDATA[Лучшие авторы месяца]]></ru>
	</translation>

	<translation>
		<nerd>Activity stream</nerd>
		<ru><![CDATA[Лента событий]]></ru>
	</translation>

	<translation>
		<nerd>Admin</nerd>
		<ru><![CDATA[Админ]]></ru>
	</translation>

	<translation>
		<nerd>Control panel</nerd>
		<ru><![CDATA[Панель управления]]></ru>
	</translation>

	<translation>
		<nerd>All members</nerd>
		<ru><![CDATA[Все пользователи]]></ru>
	</translation>

	<translation>
		<nerd>Authors</nerd>
		<ru><![CDATA[Авторы]]></ru>
	</translation>

	<translation>
		<nerd>Models</nerd>
		<ru><![CDATA[Модели]]></ru>
	</translation>

	<translation>
		<nerd>Makeup masters</nerd>
		<ru><![CDATA[Визажисты]]></ru>
	</translation>

	<translation>
		<nerd>authors</nerd>
		<ru><![CDATA[авторы]]></ru>
	</translation>

	<translation>
		<nerd>models</nerd>
		<ru><![CDATA[модели]]></ru>
	</translation>

	<translation>
		<nerd>makeup masters</nerd>
		<ru><![CDATA[визажисты]]></ru>
	</translation>

	<translation>
		<nerd>Upload photo</nerd>
		<ru><![CDATA[Загрузить фото]]></ru>
	</translation>

	<translation>
		<nerd>Vote</nerd>
		<ru><![CDATA[Голосовать]]></ru>
	</translation>

	<translation>
		<nerd>Add a new comment</nerd>
		<ru><![CDATA[Добавить комментарий]]></ru>
	</translation>

	<translation>
		<nerd>Photo name</nerd>
		<ru><![CDATA[Название работы]]></ru>
	</translation>

	<translation>
		<nerd>Uploaded by</nerd>
		<ru><![CDATA[Загрузил]]></ru>
	</translation>

	<translation>
		<nerd>Upload time</nerd>
		<ru><![CDATA[Время загрузки]]></ru>
	</translation>

	<translation>
		<nerd>Photo category</nerd>
		<ru><![CDATA[Раздел фотографии]]></ru>
	</translation>

	<translation>
		<nerd>Original size</nerd>
		<ru><![CDATA[Размер оригинала]]></ru>
	</translation>

	<translation>
		<nerd>Shown dimension</nerd>
		<ru><![CDATA[Показанный размер]]></ru>
	</translation>

	<translation>
		<nerd>File size</nerd>
		<ru><![CDATA[Размер файла]]></ru>
	</translation>

	<translation>
		<nerd>Photo team</nerd>
		<ru><![CDATA[Участники съемки]]></ru>
	</translation>

	<translation>
		<nerd>Photo albums</nerd>
		<ru><![CDATA[Фото альбомы]]></ru>
	</translation>

	<translation>
		<nerd>Author's rank in category</nerd>
		<ru><![CDATA[Ранг автора в разделе]]></ru>
	</translation>

	<translation>
		<nerd>Current rank</nerd>
		<ru><![CDATA[Текущий ранг]]></ru>
	</translation>

	<translation>
		<nerd>When photo was uploaded</nerd>
		<ru><![CDATA[Когда работа была загружена]]></ru>
	</translation>

	<translation>
		<nerd>Vote for the rank</nerd>
		<ru><![CDATA[Голосовать за рагн автора в разделе]]></ru>
	</translation>

	<translation>
		<nerd>Total marks</nerd>
		<ru><![CDATA[Всего оценок]]></ru>
	</translation>

	<translation>
		<nerd>Marks by categories</nerd>
		<ru><![CDATA[Оценки в разрезе категорий]]></ru>
	</translation>

	<translation>
		<nerd>Today's rating position</nerd>
		<ru><![CDATA[Позиция в сегодняшнем рейтинге]]></ru>
	</translation>

	<translation>
		<nerd>Photo's awards</nerd>
		<ru><![CDATA[Полученные награды]]></ru>
	</translation>

	<translation>
		<nerd>Previews</nerd>
		<ru><![CDATA[Просмотров]]></ru>
	</translation>

	<translation>
		<nerd>Comments</nerd>
		<ru><![CDATA[Комментариев]]></ru>
	</translation>

	<translation>
		<nerd>Photo activity stream</nerd>
		<ru><![CDATA[Лента событий]]></ru>
	</translation>

	<translation>
		<nerd>Photo detailes</nerd>
		<ru><![CDATA[Информация о работе]]></ru>
	</translation>

	<translation>
		<nerd>px</nerd>
		<ru><![CDATA[пикселей]]></ru>
	</translation>

	<translation>
		<nerd>Kb</nerd>
		<ru><![CDATA[Кб]]></ru>
	</translation>

	<translation>
		<nerd>Photo description</nerd>
		<ru><![CDATA[Дополнительная информация о работе]]></ru>
	</translation>

	<translation>
		<nerd>Reply to the comment</nerd>
		<ru><![CDATA[Ответить на комментарий]]></ru>
	</translation>

	<translation>
		<nerd>Comment from</nerd>
		<ru><![CDATA[Комментарий от]]></ru>
	</translation>

	<translation>
		<nerd>Comment</nerd>
		<ru><![CDATA[Комментарий]]></ru>
	</translation>

	<translation>
		<nerd>You can not leave comments</nerd>
		<ru><![CDATA[Вы не можете комментировать данную работу]]></ru>
	</translation>

	<translation>
		<nerd>Reset comment form</nerd>
		<ru><![CDATA[Очистить форму комментария]]></ru>
	</translation>

	<translation>
		<nerd>Comments length: $1 - $2 symbols</nerd>
		<ru><![CDATA[Длина комментария: $1 - $2 символов]]></ru>
	</translation>

	<translation>
		<nerd>Your delay between comments: $1 seconds</nerd>
		<ru><![CDATA[Задержка между комментариями: $1 секунд]]></ru>
	</translation>

	<translation>
		<nerd>You has already voted at $1</nerd>
		<ru><![CDATA[Вы уже проголосовали $1]]></ru>
	</translation>

	<translation>
		<nerd>Users total</nerd>
		<ru><![CDATA[Всего пользователей]]></ru>
	</translation>

	<translation>
		<nerd>Private messages total</nerd>
		<ru><![CDATA[Всего личных сообщений]]></ru>
	</translation>

	<translation>
		<nerd>Statistics</nerd>
		<ru><![CDATA[Статистика]]></ru>
	</translation>

	<translation>
		<nerd>Reload system properties</nerd>
		<ru><![CDATA[Перезагрузить системные настройки]]></ru>
	</translation>

	<translation>
		<nerd>Lock photo author: $1</nerd>
		<ru><![CDATA[Забанить автора фоторафии: $1]]></ru>
	</translation>

	<translation>
		<nerd>Time to the next comment</nerd>
		<ru><![CDATA[Время до следующего комментария]]></ru>
	</translation>

	<translation>
		<nerd>This week's photos</nerd>
		<ru><![CDATA[Работы этой недели]]></ru>
	</translation>

	<translation>
		<nerd>My Tech</nerd>
		<ru><![CDATA[Моя техника]]></ru>
	</translation>

	<translation>
		<nerd>Notifications Control</nerd>
		<ru><![CDATA[Управление уведомлениями]]></ru>
	</translation>

	<translation>
		<nerd>Photo info</nerd>
		<ru><![CDATA[Информация о работе]]></ru>
	</translation>

	<translation>
		<nerd>This month's photos</nerd>
		<ru><![CDATA[Работы этого месяца]]></ru>
	</translation>

	<translation>
		<nerd>System notifications</nerd>
		<ru><![CDATA[Системные уведомления]]></ru>
	</translation>

	<translation>
		<nerd>Lock comment author: $1</nerd>
		<ru><![CDATA[Забанить афтора комментария: $1]]></ru>
	</translation>

	<translation>
		<nerd>Private messages</nerd>
		<ru><![CDATA[Личные сообщения]]></ru>
	</translation>

	<translation>
		<nerd>Lock user</nerd>
		<ru><![CDATA[Забанить пользователя]]></ru>
	</translation>

	<translation>
		<nerd>Show photos: $1</nerd>
		<ru><![CDATA[Показать работы: $1]]></ru>
	</translation>

	<translation>
		<nerd>N/A</nerd>
		<ru><![CDATA[Н/Д]]></ru>
	</translation>

	<translation>
		<nerd>Error saving message</nerd>
		<ru><![CDATA[Ошибка сохранения сообщения]]></ru>
	</translation>

	<translation>
		<nerd>Error getting photo info</nerd>
		<ru><![CDATA[Ошибка загрузки информации о работе]]></ru>
	</translation>

	<translation>
		<nerd>Bookmarked photos</nerd>
		<ru><![CDATA[Работы в закладках]]></ru>
	</translation>

	<translation>
		<nerd>ADMIN</nerd>
		<ru><![CDATA[АДМИН]]></ru>
	</translation>

	<translation>
		<nerd>Photo comments total</nerd>
		<ru><![CDATA[Всего комментариев]]></ru>
	</translation>

	<translation>
		<nerd>Save changes</nerd>
		<ru><![CDATA[Сохранить изменения]]></ru>
	</translation>

	<translation>
		<nerd>You can leave a comment after</nerd>
		<ru><![CDATA[Вы можете оставить комментарий через]]></ru>
	</translation>

	<translation>
		<nerd>Favorite photos</nerd>
		<ru><![CDATA[Избранные работы]]></ru>
	</translation>

	<translation>
		<nerd>The member does not have enough photos in category $1 ( there are $2 photos but has to be at least $3 ones ).</nerd>
		<ru><![CDATA[Пользователь не имеет достаточного количества работ в разделе $1 ( у него загружено только $2 работ(ы), а должно быть не менее $3 )]]></ru>
	</translation>

	<translation>
		<nerd>Photos total</nerd>
		<ru><![CDATA[Всего работ]]></ru>
	</translation>

	<translation>
		<nerd>My Card</nerd>
		<ru><![CDATA[Моя карточка]]></ru>
	</translation>

	<translation>
		<nerd>Max accessible at voting time mark: $1</nerd>
		<ru><![CDATA[Максимальная оценка, доступная на момент голосования: $1]]></ru>
	</translation>

	<translation>
		<nerd>Black List</nerd>
		<ru><![CDATA[Черный список]]></ru>
	</translation>

	<translation>
		<nerd>Clear system cache</nerd>
		<ru><![CDATA[Очистить системный кеш]]></ru>
	</translation>

	<translation>
		<nerd>Best of $1</nerd>
		<ru><![CDATA[Лучшие $1]]></ru>
	</translation>

	<translation>
		<nerd>My Albums</nerd>
		<ru><![CDATA[Мои альбомы]]></ru>
	</translation>

	<translation>
		<nerd>Best yesterday's photos</nerd>
		<ru><![CDATA[Лучшие работы за вчера]]></ru>
	</translation>

	<translation>
		<nerd>Password</nerd>
		<ru><![CDATA[Пароль]]></ru>
	</translation>

	<translation>
		<nerd>Warning</nerd>
		<ru><![CDATA[Предупреждение]]></ru>
	</translation>

	<translation>
		<nerd>You can not vote for the member's rank in category. Click to see detailed message</nerd>
		<ru><![CDATA[Вы не можете проголосовать за ранг пользователя в разделе. Кликните чтобы посмотреть дополнительную информацию]]></ru>
	</translation>

	<translation>
		<nerd>Max accessible at voting time for $1 mark</nerd>
		<ru><![CDATA[Максимальная оценка, доступная $1 на момент голосования]]></ru>
	</translation>

	<translation>
		<nerd>Activity notifications</nerd>
		<ru><![CDATA[Уведомления о действиях пользователей]]></ru>
	</translation>

	<translation>
		<nerd>Send private message to $1</nerd>
		<ru><![CDATA[Отправить личное сообщение $1]]></ru>
	</translation>

	<translation>
		<nerd>Send private message to</nerd>
		<ru><![CDATA[Отправить личное сообщение]]></ru>
	</translation>

	<translation>
		<nerd>Scheduler</nerd>
		<ru><![CDATA[Планировщик]]></ru>
	</translation>

	<translation>
		<nerd>Summary photo's mark in this category</nerd>
		<ru><![CDATA[Суммарные оценки работы в этом разделе]]></ru>
	</translation>

	<translation>
		<nerd>You can not delete a comment which you are editing now</nerd>
		<ru><![CDATA[Вы не можете удалить комментарий который в данный момент редактируете]]></ru>
	</translation>

	<translation>
		<nerd>Lock member: $1</nerd>
		<ru><![CDATA[Забанить пользователя: $1]]></ru>
	</translation>

	<translation>
		<nerd>Translated</nerd>
		<ru><![CDATA[Переведенные]]></ru>
	</translation>

	<translation>
		<nerd>has been added to</nerd>
		<ru><![CDATA[был добавлен в]]></ru>
	</translation>

	<translation>
		<nerd>Delete photo</nerd>
		<ru><![CDATA[Удалить работу]]></ru>
	</translation>

	<translation>
		<nerd>Your set mark for $1: $2</nerd>
		<ru><![CDATA[Ваша оценка в категории $1: $2]]></ru>
	</translation>

	<translation>
		<nerd>The message has been sent</nerd>
		<ru><![CDATA[Сообщение отправлено]]></ru>
	</translation>

	<translation>
		<nerd>Comments to me</nerd>
		<ru><![CDATA[Полученные комментарии]]></ru>
	</translation>

	<translation>
		<nerd>Zero rank in category '$1'</nerd>
		<ru><![CDATA[Нулевой ранг в разделе '$1']]></ru>
	</translation>

	<translation>
		<nerd>All photos</nerd>
		<ru><![CDATA[Все работы]]></ru>
	</translation>

	<translation>
		<nerd>$1 - votes</nerd>
		<ru><![CDATA[$1 - голоса]]></ru>
	</translation>

	<translation>
		<nerd>Member $1, photo album '$2'</nerd>
		<ru><![CDATA[$1, фотоальбом '$2']]></ru>
	</translation>

	<translation>
		<nerd>The message has been sent to</nerd>
		<ru><![CDATA[Сообщение было отправлено]]></ru>
	</translation>

	<translation>
		<nerd>Complaint copyright</nerd>
		<ru><![CDATA[Пожаловаться на нарушение авторства]]></ru>
	</translation>

	<translation>
		<nerd>You can not vote for the member rank in category $1:</nerd>
		<ru><![CDATA[Вы не можете голосовать за ранг пользователя в разделе $1:]]></ru>
	</translation>

	<translation>
		<nerd>Comments subscribe</nerd>
		<ru><![CDATA[Подписка на комментарии]]></ru>
	</translation>

	<translation>
		<nerd>My Photos</nerd>
		<ru><![CDATA[Мои работы]]></ru>
	</translation>

	<translation>
		<nerd>Statistic</nerd>
		<ru><![CDATA[Статистика]]></ru>
	</translation>

	<translation>
		<nerd>Voting Categories</nerd>
		<ru><![CDATA[Категории голосования]]></ru>
	</translation>

	<translation>
		<nerd>Today's photos</nerd>
		<ru><![CDATA[Сегодняшние работы]]></ru>
	</translation>

	<translation>
		<nerd>Yesterday's photos</nerd>
		<ru><![CDATA[Вчерашние работы]]></ru>
	</translation>

	<translation>
		<nerd>Clear system cache?</nerd>
		<ru><![CDATA[Очистить системный кеш?]]></ru>
	</translation>

	<translation>
		<nerd>Best week's photos</nerd>
		<ru><![CDATA[Лучшие работы этой недели]]></ru>
	</translation>

	<translation>
		<nerd>There is not enough photos in category '$1' to have a rank</nerd>
		<ru><![CDATA[Недостаточно работ в разделе '$1'] чтобы иметь ранг]></ru>
	</translation>

	<translation>
		<nerd>Change password</nerd>
		<ru><![CDATA[Изменить пароль]]></ru>
	</translation>

	<translation>
		<nerd>My comments</nerd>
		<ru><![CDATA[Мои комментарии]]></ru>
	</translation>

	<translation>
		<nerd>My Avatar</nerd>
		<ru><![CDATA[Мой аватар]]></ru>
	</translation>

	<translation>
		<nerd>Actions type</nerd>
		<ru><![CDATA[Тим события]]></ru>
	</translation>

	<translation>
		<nerd>Your card</nerd>
		<ru><![CDATA[Ваша карточка]]></ru>
	</translation>

	<translation>
		<nerd>Photo previews total</nerd>
		<ru><![CDATA[Всего просмотров]]></ru>
	</translation>

	<translation>
		<nerd>Job $1 is performed successfully</nerd>
		<ru><![CDATA[Задача $1 выполнена успешно]]></ru>
	</translation>

	<translation>
		<nerd>$1 - avatar</nerd>
		<ru><![CDATA[$1 - аватар]]></ru>
	</translation>

	<translation>
		<nerd>Remember me</nerd>
		<ru><![CDATA[Запомнить меня]]></ru>
	</translation>

	<translation>
		<nerd>DB upgrade</nerd>
		<ru><![CDATA[Апгрейд БД]]></ru>
	</translation>

	<translation>
		<nerd>Profile settings</nerd>
		<ru><![CDATA[Настройки профайла]]></ru>
	</translation>

	<translation>
		<nerd>Delete comment?</nerd>
		<ru><![CDATA[Удалить комментарий?]]></ru>
	</translation>

	<translation>
		<nerd>Absolute best</nerd>
		<ru><![CDATA[Абсолютный рейтинг]]></ru>
	</translation>

	<translation>
		<nerd>Reply to $1$2</nerd>
		<ru><![CDATA[Ответить $1$2]]></ru>
	</translation>

	<translation>
		<nerd>My Team</nerd>
		<ru><![CDATA[Моя команда]]></ru>
	</translation>

	<translation>
		<nerd>Editing comment</nerd>
		<ru><![CDATA[Редактирование комментария]]></ru>
	</translation>

	<translation>
		<nerd>Favorite Members</nerd>
		<ru><![CDATA[Избранные пользователи]]></ru>
	</translation>

	<translation>
		<nerd>Reload translations?</nerd>
		<ru><![CDATA[Перезагрузить переводы?]]></ru>
	</translation>

	<translation>
		<nerd>Reload translations</nerd>
		<ru><![CDATA[Перезагрузить переводы]]></ru>
	</translation>

	<translation>
		<nerd>Set by $1 mark</nerd>
		<ru><![CDATA[Оценки выставленные $1]]></ru>
	</translation>

	<translation>
		<nerd>Friends</nerd>
		<ru><![CDATA[Друзья]]></ru>
	</translation>

	<translation>
		<nerd>Show member card: $1</nerd>
		<ru><![CDATA[Показать карточку: $1]]></ru>
	</translation>

	<translation>
		<nerd>Reload system properties?</nerd>
		<ru><![CDATA[Перезагрузить системные настройки?]]></ru>
	</translation>

	<translation>
		<nerd>$1: photo card</nerd>
		<ru><![CDATA[$1: карточка работы]]></ru>
	</translation>

	<translation>
		<nerd>Send complaint message</nerd>
		<ru><![CDATA[Пожаловаться]]></ru>
	</translation>

	<translation>
		<nerd>Delete comment</nerd>
		<ru><![CDATA[Удалить комментарий]]></ru>
	</translation>

	<translation>
		<nerd>Edit photo</nerd>
		<ru><![CDATA[Редактировать работу]]></ru>
	</translation>

	<translation>
		<nerd>Untranslated</nerd>
		<ru><![CDATA[Непереведенные]]></ru>
	</translation>

	<translation>
		<nerd>To the top of page</nerd>
		<ru><![CDATA[Наверх страницы]]></ru>
	</translation>

	<translation>
		<nerd>Comment must be more then $1 and less then $2 symbols</nerd>
		<ru><![CDATA[Комментарий должен быть больше чем $1 и меньше чем $2 символов]]></ru>
	</translation>

	<translation>
		<nerd>The scheduler is stopped!</nerd>
		<ru><![CDATA[Планировщик остановлен!]]></ru>
	</translation>

	<translation>
		<nerd>Configuration</nerd>
		<ru><![CDATA[Конфигурация системы]]></ru>
	</translation>

	<translation>
		<nerd>$1: photos in category '$2' ( $3 )</nerd>
		<ru><![CDATA[$1: работы из раздела '$2' ( $3 )]]></ru>
	</translation>

	<translation>
		<nerd>$1: all photos ( $2 )</nerd>
		<ru><![CDATA[$1: все работы ( $2 )]]></ru>
	</translation>

	<translation>
		<nerd>Admin notifications</nerd>
		<ru><![CDATA[Уведомления администрации]]></ru>
	</translation>

	<translation>
		<nerd>Best today's photos</nerd>
		<ru><![CDATA[Лучшие работы сегодня]]></ru>
	</translation>

	<translation>
		<nerd>Delete photo?</nerd>
		<ru><![CDATA[Удалить работу?]]></ru>
	</translation>

	<translation>
		<nerd>Best month's photos</nerd>
		<ru><![CDATA[Лучшие работы месяца]]></ru>
	</translation>

	<translation>
		<nerd>Number of users who voted for the photo in this category</nerd>
		<ru><![CDATA[Количество пользователей, которые проголосовали за работу в этой категории]]></ru>
	</translation>

	<translation>
		<nerd>Send message</nerd>
		<ru><![CDATA[Отправить сообщение]]></ru>
	</translation>

	<translation>
		<nerd>$1 - previews</nerd>
		<ru><![CDATA[$1 - просмотры]]></ru>
	</translation>

	<translation>
		<nerd>On new photos</nerd>
		<ru><![CDATA[На новые работы]]></ru>
	</translation>

	<translation>
		<nerd>On new comments</nerd>
		<ru><![CDATA[На новые комментарии]]></ru>
	</translation>

	<translation>
		<nerd>Anonymous Days</nerd>
		<ru><![CDATA[Дни анонимной загрузки]]></ru>
	</translation>

	<translation>
		<nerd>Group operations with selected photos</nerd>
		<ru><![CDATA[Групповые операции с отмеченными работами]]></ru>
	</translation>

	<translation>
		<nerd>See all photos</nerd>
		<ru><![CDATA[Все работы]]></ru>
	</translation>

	<translation>
		<nerd>The photo is marked as 'Contains nude content'</nerd>
		<ru><![CDATA[Работа помечена как содержащая НЮ контент]]></ru>
	</translation>

	<translation>
		<nerd>Marks for last $1 days</nerd>
		<ru><![CDATA[Оценки за последние $1 дня]]></ru>
	</translation>

	<translation>
		<nerd>Rank in category '$1' : $2</nerd>
		<ru><![CDATA[ранг в разделе '$1' : $2]]></ru>
	</translation>

	<translation>
		<nerd>Lock</nerd>
		<ru><![CDATA[Забанить]]></ru>
	</translation>

	<translation>
		<nerd>Today's marks</nerd>
		<ru><![CDATA[Оценки полученные сегодня]]></ru>
	</translation>

	<translation>
		<nerd>Pages</nerd>
		<ru><![CDATA[Страниц]]></ru>
	</translation>

	<translation>
		<nerd>Anonymous till</nerd>
		<ru><![CDATA[Анонимность до]]></ru>
	</translation>

	<translation>
		<nerd>Change password</nerd>
		<ru><![CDATA[Изменить пароль]]></ru>
	</translation>

	<translation>
		<nerd>Items on page</nerd>
		<ru><![CDATA[На странице]]></ru>
	</translation>

	<translation>
		<nerd>Private message text</nerd>
		<ru><![CDATA[Текст личного сообщения]]></ru>
	</translation>

	<translation>
		<nerd>Nude content</nerd>
		<ru><![CDATA[НЮ контент]]></ru>
	</translation>

	<translation>
		<nerd>Comments: $1</nerd>
		<ru><![CDATA[Комментарии: $1]]></ru>
	</translation>

	<translation>
		<nerd>Please, select group operation first</nerd>
		<ru><![CDATA[Пожалуйста, выберите групповую оперция сперва]]></ru>
	</translation>

	<translation>
		<nerd>Translator</nerd>
		<ru><![CDATA[Переводчик]]></ru>
	</translation>

	<translation>
		<nerd>$1: photos from album '$2' ( $3 )</nerd>
		<ru><![CDATA[$1: работы в альбоме '$2' ( $3 )]]></ru>
	</translation>

	<translation>
		<nerd>Show photos on $1</nerd>
		<ru><![CDATA[Показать работы на $1]]></ru>
	</translation>

	<translation>
		<nerd>$1 menu</nerd>
		<ru><![CDATA[$1 меню]]></ru>
	</translation>

	<translation>
		<nerd>Top $1 best photos</nerd>
		<ru><![CDATA[Top $1 лучших работ]]></ru>
	</translation>

	<translation>
		<nerd>Send complaint message:</nerd>
		<ru><![CDATA[Пожаловаться на:]]></ru>
	</translation>

	<translation>
		<nerd>The photo is posted anonymously</nerd>
		<ru><![CDATA[Работа размещена анонимно]]></ru>
	</translation>

	<translation>
		<nerd>Items</nerd>
		<ru><![CDATA[Всего]]></ru>
	</translation>

	<translation>
		<nerd>The Author did not allow commenting</nerd>
		<ru><![CDATA[Автор запретил комментарии]]></ru>
	</translation>

	<translation>
		<nerd>Message</nerd>
		<ru><![CDATA[Сообщение]]></ru>
	</translation>

	<translation>
		<nerd>that have got at least $1 marks</nerd>
		<ru><![CDATA[набравшие не менее $1 баллов]]></ru>
	</translation>

	<translation>
		<nerd>Show all photos of the list</nerd>
		<ru><![CDATA[Показать все работы в списке]]></ru>
	</translation>

	<translation>
		<nerd>Pages $1 - $2</nerd>
		<ru><![CDATA[Страницы $1 - $2]]></ru>
	</translation>

	<translation>
		<nerd>Admin notifications</nerd>
		<ru><![CDATA[Уведомления от админа]]></ru>
	</translation>

	<translation>
		<nerd>Previews: $1</nerd>
		<ru><![CDATA[Просмотры: $1]]></ru>
	</translation>

	<translation>
		<nerd>The author allowed voting to members only</nerd>
		<ru><![CDATA[Автор разрешил голосование только для членов клуба]]></ru>
	</translation>

	<translation>
		<nerd>Please, select at least one photo first</nerd>
		<ru><![CDATA[Пожалуйста, выделите сперва хотя бы одну работу]]></ru>
	</translation>

	<translation>
		<nerd>Best for $1 days</nerd>
		<ru><![CDATA[Лучшие за $1 дня]]></ru>
	</translation>

	<translation>
		<nerd>$1 - previews</nerd>
		<ru><![CDATA[$1 - просмотры]]></ru>
	</translation>

	<translation>
		<nerd>Genres</nerd>
		<ru><![CDATA[Разделы фотографии]]></ru>
	</translation>

	<translation>
		<nerd>Sorry, but page not found on the server</nerd>
		<ru><![CDATA[Извините, но такой страницы на сервере нет]]></ru>
	</translation>

	<translation>
		<nerd>Error 404 - Page not found</nerd>
		<ru><![CDATA[Ошибка 404 - страница не найдена]]></ru>
	</translation>

	<translation>
		<nerd>Please, select at least one category</nerd>
		<ru><![CDATA[Пожалуйста, выделите сперва хотя бы один раздел]]></ru>
	</translation>

	<translation>
		<nerd>The author allowed commenting to members only</nerd>
		<ru><![CDATA[Автор разрешил комментарии только членам клуба]]></ru>
	</translation>

	<translation>
		<nerd>Full activity stream</nerd>
		<ru><![CDATA[Вся лента событий]]></ru>
	</translation>

	<translation>
		<nerd>Error!</nerd>
		<ru><![CDATA[Ошибка!]]></ru>
	</translation>

	<translation>
		<nerd>Error</nerd>
		<ru><![CDATA[Ошибка]]></ru>
	</translation>

	<translation>
		<nerd>Time: $1</nerd>
		<ru><![CDATA[Время: $1]]></ru>
	</translation>

	<translation>
		<nerd>Sorry, but you do not have permission to perform this operation</nerd>
		<ru><![CDATA[Извините, но у вас нет доступа к данной функциональности]]></ru>
	</translation>

	<translation>
		<nerd>Oops!</nerd>
		<ru><![CDATA[Ой!]]></ru>
	</translation>

	<translation>
		<nerd>The Author denied voting</nerd>
		<ru><![CDATA[Автор запретил голосование]]></ru>
	</translation>

	<translation>
		<nerd>voting time: $1</nerd>
		<ru><![CDATA[за период: <b>$1</b>]]></ru>
	</translation>

	<translation>
		<nerd>No photos correspond to the criterias</nerd>
		<ru><![CDATA[Работ по данным критериям не найдено]]></ru>
	</translation>

	<translation>
		<nerd>Jobs</nerd>
		<ru><![CDATA[Задачи]]></ru>
	</translation>

	<translation>
		<nerd>posted in period from</nerd>
		<ru><![CDATA[загруженные с $1]]></ru>
	</translation>

	<translation>
		<nerd>to $1</nerd>
		<ru><![CDATA[по $1]]></ru>
	</translation>

	<translation>
		<nerd>Info</nerd>
		<ru><![CDATA[Информация]]></ru>
	</translation>

	<translation>
		<nerd>Invert selection</nerd>
		<ru><![CDATA[Инвертировать выделение]]></ru>
	</translation>

	<translation>
		<nerd>Send email</nerd>
		<ru><![CDATA[Написать письмо]]></ru>
	</translation>

	<translation>
		<nerd>This functionality has not been implemented yet...</nerd>
		<ru><![CDATA[Эта функциональность еще не реализована...]]></ru>
	</translation>

	<translation>
		<nerd>$1 $2 days</nerd>
		<ru><![CDATA[$1 $2 дней]]></ru>
	</translation>

	<translation>
		<nerd>You have already voted when member's rank is $1 in category '$2'</nerd>
		<ru><![CDATA[Вы уже голосовали когда ранг пользователя был $1 в разделе '$2']]></ru>
	</translation>

	<translation>
		<nerd>is duplicated value</nerd>
		<ru><![CDATA[повторяющееся значение]]></ru>
	</translation>

	<translation>
		<nerd>Click to see full size</nerd>
		<ru><![CDATA[Кликните чтобы посмотреть в полном размере]]></ru>
	</translation>

	<translation>
		<nerd>Voting error</nerd>
		<ru><![CDATA[Ошибка голосования]]></ru>
	</translation>

	<translation>
		<nerd>Success</nerd>
		<ru><![CDATA[Успешно]]></ru>
	</translation>

	<translation>
		<nerd>Rank in category '$1': $2</nerd>
		<ru><![CDATA[Ранг в разделе '$1': $2]]></ru>
	</translation>

	<translation>
		<nerd>Last activity time</nerd>
		<ru><![CDATA[Время последней активности]]></ru>
	</translation>

	<translation>
		<nerd>Your marks have been saved</nerd>
		<ru><![CDATA[Ваше голосование принято]]></ru>
	</translation>

	<translation>
		<nerd>The member does not deserve his rank $1 (-$2) in category '$3'</nerd>
		<ru><![CDATA[Пользователь не заслуживает свой ранг $1 (-$2) в разделе '$3']]></ru>
	</translation>

	<translation>
		<nerd>The member deserves higher rank than his current one $1 (+$2) in category in '$3'</nerd>
		<ru><![CDATA[Пользователь заслуживает более высокий ранг $1 (+$2) в разделе '$3']]></ru>
	</translation>

	<translation>
		<nerd>There are $1 point(s) more is necessary to achieve rank $2 in category '$3'</nerd>
		<ru><![CDATA[Вам необходимо набрать $1 балл(ов) чтобы достичь ранга $2 в разделе '$3']]></ru>
	</translation>

	<translation>
		<nerd>The photos $1 has voted recently for</nerd>
		<ru><![CDATA[Работы, которые $1 недавно оценил]]></ru>
	</translation>

	<translation>
		<nerd>Click to see who voted for the rank in category $1</nerd>
		<ru><![CDATA[Кликните, чтобы увидеть кто голосовал за ранг в разделе $1]]></ru>
	</translation>

	<translation>
		<nerd>$1: show all photos</nerd>
		<ru><![CDATA[$1: показать все работы]]></ru>
	</translation>

	<translation>
		<nerd>Photos and ranks</nerd>
		<ru><![CDATA[Работы и ранги по разделам]]></ru>
	</translation>

	<translation>
		<nerd>Personal information</nerd>
		<ru><![CDATA[Персональные данные]]></ru>
	</translation>

	<translation>
		<nerd>Last photos of $1</nerd>
		<ru><![CDATA[Последние работы $1]]></ru>
	</translation>

	<translation>
		<nerd>Membership type</nerd>
		<ru><![CDATA[Тип членства]]></ru>
	</translation>

	<translation>
		<nerd>Change avatar</nerd>
		<ru><![CDATA[Изменить аватар]]></ru>
	</translation>

	<translation>
		<nerd>Photos in category '$1': $2</nerd>
		<ru><![CDATA[Работы в категории '$1': $2]]></ru>
	</translation>

	<translation>
		<nerd>Last photos of visitors who viewed $1's photos recently</nerd>
		<ru><![CDATA[Последние работы посетителей, недавно смотревших работы $1]]></ru>
	</translation>

	<translation>
		<nerd>Gender</nerd>
		<ru><![CDATA[Пол]]></ru>
	</translation>

	<translation>
		<nerd>Email</nerd>
		<ru><![CDATA[Электронный адрес]]></ru>
	</translation>

	<translation>
		<nerd>Birthday</nerd>
		<ru><![CDATA[День рождения]]></ru>
	</translation>

	<translation>
		<nerd>Member self description</nerd>
		<ru><![CDATA[Дополнительная информация о пользователе]]></ru>
	</translation>

	<translation>
		<nerd>Edit data</nerd>
		<ru><![CDATA[Редактировать данные]]></ru>
	</translation>

	<translation>
		<nerd>Member name</nerd>
		<ru><![CDATA[Имя]]></ru>
	</translation>

	<translation>
		<nerd>Status</nerd>
		<ru><![CDATA[Статус]]></ru>
	</translation>

	<translation>
		<nerd>Edit member data: $1</nerd>
		<ru><![CDATA[Редактировать данные: $1]]></ru>
	</translation>

	<translation>
		<nerd>Notifications about new photos</nerd>
		<ru><![CDATA[Уведомление о новых работах]]></ru>
	</translation>

	<translation>
		<nerd>No team</nerd>
		<ru><![CDATA[Команды нет]]></ru>
	</translation>

	<translation>
		<nerd>Total photos</nerd>
		<ru><![CDATA[Всего работ]]></ru>
	</translation>

	<translation>
		<nerd>Reset activity filter</nerd>
		<ru><![CDATA[Сбросить фильтр]]></ru>
	</translation>

	<translation>
		<nerd>$1's notifications about new comments</nerd>
		<ru><![CDATA[$1: уведомления о новых комментариях]]></ru>
	</translation>

	<translation>
		<nerd>Favorite members</nerd>
		<ru><![CDATA[Избранные пользователи]]></ru>
	</translation>

	<translation>
		<nerd>Friends of $1</nerd>
		<ru><![CDATA[$1: друзья]]></ru>
	</translation>

	<translation>
		<nerd>Written by $1 comments</nerd>
		<ru><![CDATA[Комментарии, которые написал(а) $1]]></ru>
	</translation>

	<translation>
		<nerd>Added in Favorites by</nerd>
		<ru><![CDATA[Добавлен в избранные]]></ru>
	</translation>

	<translation>
		<nerd>Notifications about new comments</nerd>
		<ru><![CDATA[Уведомление о новых работах]]></ru>
	</translation>

	<translation>
		<nerd>Team</nerd>
		<ru><![CDATA[Команда]]></ru>
	</translation>

	<translation>
		<nerd>$1's favorite members</nerd>
		<ru><![CDATA[$1: избранные пользователи]]></ru>
	</translation>

	<translation>
		<nerd>No photo</nerd>
		<ru><![CDATA[Работ нет]]></ru>
	</translation>

	<translation>
		<nerd>$1's favorite photos</nerd>
		<ru><![CDATA[$1: избранные работы]]></ru>
	</translation>

	<translation>
		<nerd>$1's black list</nerd>
		<ru><![CDATA[$1: черный список]]></ru>
	</translation>

	<translation>
		<nerd>Received by $1 comments</nerd>
		<ru><![CDATA[Полученные $1 комментарии]]></ru>
	</translation>

	<translation>
		<nerd>Received unread comments</nerd>
		<ru><![CDATA[Полученные непрочитанные комментарии]]></ru>
	</translation>

	<translation>
		<nerd>Last photos from album '$1' - $2 photos</nerd>
		<ru><![CDATA[Последние работы из альбома '$1' - $2 работ]]></ru>
	</translation>

	<translation>
		<nerd>Written comments</nerd>
		<ru><![CDATA[Написанные комментарии]]></ru>
	</translation>

	<translation>
		<nerd>$1's bookmarked photos</nerd>
		<ru><![CDATA[$1: работы в закладках]]></ru>
	</translation>

	<translation>
		<nerd>Activity filter: $1</nerd>
		<ru><![CDATA[Фильтр: $1]]></ru>
	</translation>

	<translation>
		<nerd>You have $1 new comment(s)</nerd>
		<ru><![CDATA[У вас $1 новых комментариев]]></ru>
	</translation>

	<translation>
		<nerd>Mark ALL unread comments as read?</nerd>
		<ru><![CDATA[Пометить ВСЕ непрочитанные комменатрии как прочитанные?]]></ru>
	</translation>

	<translation>
		<nerd>Black list</nerd>
		<ru><![CDATA[Черный список]]></ru>
	</translation>

	<translation>
		<nerd>Mark all as read</nerd>
		<ru><![CDATA[Пометить все как прочитанное]]></ru>
	</translation>

	<translation>
		<nerd>$1: the best photos. Total $2</nerd>
		<ru><![CDATA[$1: лучшие работы. Всего $2]]></ru>
	</translation>

	<translation>
		<nerd>voted for rank of $1 in category $2 ( $3 )</nerd>
		<ru><![CDATA[голосовал за ранк $1 в разделе $2 ( $3 )]]></ru>
	</translation>

	<translation>
		<nerd>$1 marked $2 photo(s) as $3</nerd>
		<ru><![CDATA[$1 оценил $2 работ критерием $3]]></ru>
	</translation>

	<translation>
		<nerd>Submit</nerd>
		<ru><![CDATA[Отправить]]></ru>
	</translation>

	<translation>
		<nerd><![CDATA[voted for photo $1<br />$2]]></nerd>
		<ru><![CDATA[оценил работу $1<br />$2]]></ru>
	</translation>

	<translation>
		<nerd>Received comments</nerd>
		<ru><![CDATA[Полученные комментарии]]></ru>
	</translation>

	<translation>
		<nerd>id</nerd>
		<ru><![CDATA[id]]></ru>
	</translation>

	<translation>
		<nerd>System</nerd>
		<ru><![CDATA[Система]]></ru>
	</translation>

	<translation>
		<nerd>Comments of $1</nerd>
		<ru><![CDATA[Комментарии $1]]></ru>
	</translation>

	<translation>
		<nerd>Summary marks set for $1: $2</nerd>
		<ru><![CDATA[Суммарно выставленные оценки по критерию $1: $2]]></ru>
	</translation>

	<translation>
		<nerd>No items</nerd>
		<ru><![CDATA[Ничего не найдено]]></ru>
	</translation>

	<translation>
		<nerd>Not accessible</nerd>
		<ru><![CDATA[Недоступно]]></ru>
	</translation>

	<translation>
		<nerd>uploaded photo $1</nerd>
		<ru><![CDATA[загрузил работу $1]]></ru>
	</translation>

	<translation>
		<nerd>Generate preview</nerd>
		<ru><![CDATA[Генерировать превью]]></ru>
	</translation>

	<translation>
		<nerd>No</nerd>
		<ru><![CDATA[Нет]]></ru>
	</translation>

	<translation>
		<nerd>Yes</nerd>
		<ru><![CDATA[Да]]></ru>
	</translation>

	<translation>
		<nerd>$1's notifications about new photos</nerd>
		<ru><![CDATA[$1: уведомления о новых работах]]></ru>
	</translation>

	<translation>
		<nerd>Photo: $1</nerd>
		<ru><![CDATA[Работа: $1]]></ru>
	</translation>

	<translation>
		<nerd>$1: received but unread comments</nerd>
		<ru><![CDATA[$1: полученные, но еще непрочитанные комментарии]]></ru>
	</translation>

	<translation>
		<nerd>Photos was appraised '$1' by $2</nerd>
		<ru><![CDATA[Работы оцененные по критерию '$1' $2]]></ru>
	</translation>

	<translation>
		<nerd>commented photo $1</nerd>
		<ru><![CDATA[оставил комментарий к работе $1]]></ru>
	</translation>

	<translation>
		<nerd>comments</nerd>
		<ru><![CDATA[комментарии]]></ru>
	</translation>

	<translation>
		<nerd>marks</nerd>
		<ru><![CDATA[оценки]]></ru>
	</translation>

	<translation>
		<nerd>Shown size</nerd>
		<ru><![CDATA[Показанный размер]]></ru>
	</translation>

	<translation>
		<nerd>Unread</nerd>
		<ru><![CDATA[Непрочитанные]]></ru>
	</translation>

	<translation>
		<nerd>Last set marks</nerd>
		<ru><![CDATA[Последние выставленные оценки]]></ru>
	</translation>

	<translation>
		<nerd>The Best</nerd>
		<ru><![CDATA[Лучшие]]></ru>
	</translation>

	<translation>
		<nerd>Alert</nerd>
		<ru><![CDATA[Предупреждение]]></ru>
	</translation>

	<translation>
		<nerd>second(s)</nerd>
		<ru><![CDATA[секунд]]></ru>
	</translation>

	<translation>
		<nerd>seconds</nerd>
		<ru><![CDATA[секунд]]></ru>
	</translation>

	<translation>
		<nerd>Users generation</nerd>
		<ru><![CDATA[Генерирование пользователей]]></ru>
	</translation>

	<translation>
		<nerd>User status recalculation</nerd>
		<ru><![CDATA[Пересчет пользовательских статусов]]></ru>
	</translation>

	<translation>
		<nerd>The task is active</nerd>
		<ru><![CDATA[Задача активна]]></ru>
	</translation>

	<translation>
		<nerd>Scheduled task job</nerd>
		<ru><![CDATA[Запланированная задача]]></ru>
	</translation>

	<translation>
		<nerd>Task type</nerd>
		<ru><![CDATA[Тип задачи]]></ru>
	</translation>

	<translation>
		<nerd>Scheduled task type</nerd>
		<ru><![CDATA[Тип запланированной задачи]]></ru>
	</translation>

	<translation>
		<nerd>Deactivate selected scheduler tasks</nerd>
		<ru><![CDATA[Деактивировать выделенные задачи планировщика]]></ru>
	</translation>

	<translation>
		<nerd>The Scheduler is running. Click to stop scheduler.</nerd>
		<ru><![CDATA[Планировщик запущен. Кликните чтобы остановить.]]></ru>
	</translation>

	<translation>
		<nerd>Photos import</nerd>
		<ru><![CDATA[Импорт фотографий]]></ru>
	</translation>

	<translation>
		<nerd>Activate selected scheduler tasks</nerd>
		<ru><![CDATA[Активировать выделенные задачи планировщика]]></ru>
	</translation>

	<translation>
		<nerd>Photo rating for period recalculation</nerd>
		<ru><![CDATA[Пересчет рейтинга работ за период]]></ru>
	</translation>

	<translation>
		<nerd>Recreate indexes and constraints</nerd>
		<ru><![CDATA[Пересоздание индексов]]></ru>
	</translation>

	<translation>
		<nerd>Task parameters</nerd>
		<ru><![CDATA[Параметры задачи]]></ru>
	</translation>

	<translation>
		<nerd>Job: #$1</nerd>
		<ru><![CDATA[Задача: #$1]]></ru>
	</translation>

	<translation>
		<nerd>Photo storage synchronization</nerd>
		<ru><![CDATA[Синхронизация фотохранилища]]></ru>
	</translation>

	<translation>
		<nerd>Scheduled task is scheduled</nerd>
		<ru><![CDATA[Задача планировщика запланирована]]></ru>
	</translation>

	<translation>
		<nerd>Task name</nerd>
		<ru><![CDATA[Название задачи]]></ru>
	</translation>

	<translation>
		<nerd>Dir</nerd>
		<ru><![CDATA[Каталог]]></ru>
	</translation>

	<translation>
		<nerd>View info '$1'</nerd>
		<ru><![CDATA[Посмотреть информацию '$1']]></ru>
	</translation>

	<translation>
		<nerd>Activate selected tasks?</nerd>
		<ru><![CDATA[Активировать выделенные задачи?]]></ru>
	</translation>

	<translation>
		<nerd>Delete selected scheduler tasks</nerd>
		<ru><![CDATA[Удалить выделенные задачи]]></ru>
	</translation>

	<translation>
		<nerd>Chain job</nerd>
		<ru><![CDATA[Комплексная задача]]></ru>
	</translation>

	<translation>
		<nerd>Scheduled task job id</nerd>
		<ru><![CDATA[ID запланированной задачи]]></ru>
	</translation>

	<translation>
		<nerd>Photo actions: previews</nerd>
		<ru><![CDATA[Действия с работами: просмотры]]></ru>
	</translation>

	<translation>
		<nerd>Photo actions: voting</nerd>
		<ru><![CDATA[Действия с работами: голосование]]></ru>
	</translation>

	<translation>
		<nerd>Photo actions: comments</nerd>
		<ru><![CDATA[Действия с работами: комментарии]]></ru>
	</translation>

	<translation>
		<nerd>Voting for users ranks in categories generation</nerd>
		<ru><![CDATA[Генерирование голосования за пользовательский ранг в разделах]]></ru>
	</translation>

	<translation>
		<nerd>$1 - photo info</nerd>
		<ru><![CDATA[$1 - информация о работе]]></ru>
	</translation>

	<translation>
		<nerd>Scheduled</nerd>
		<ru><![CDATA[Запланированно]]></ru>
	</translation>

	<translation>
		<nerd>Members ranks in genres recalculation</nerd>
		<ru><![CDATA[Пересчет пользовательских рангов по разделам]]></ru>
	</translation>

	<translation>
		<nerd>Scheduled task is active</nerd>
		<ru><![CDATA[Задача планировщика активна]]></ru>
	</translation>

	<translation>
		<nerd>Delete task '$1'</nerd>
		<ru><![CDATA[Удалить задачу '$1']]></ru>
	</translation>

	<translation>
		<nerd>Deactivate selected tasks?</nerd>
		<ru><![CDATA[Деактивировать выделенные задачи?]]></ru>
	</translation>

	<translation>
		<nerd>Delete selected tasks?</nerd>
		<ru><![CDATA[Удалить выделенные задачи?]]></ru>
	</translation>

	<translation>
		<nerd>Scheduled task name</nerd>
		<ru><![CDATA[Название задачи планировщика]]></ru>
	</translation>

	<translation>
		<nerd>Edit scheduler task $1: '$2'</nerd>
		<ru><![CDATA[Редактировать задачу планировщика $1: '$2']]></ru>
	</translation>

	<translation>
		<nerd>The task is inactive</nerd>
		<ru><![CDATA[Задача неактивна]]></ru>
	</translation>

	<translation>
		<nerd>Photo previews generation</nerd>
		<ru><![CDATA[Генерация фото превью]]></ru>
	</translation>

	<translation>
		<nerd>Scheduled task' parameters</nerd>
		<ru><![CDATA[Параметры задач планировщика]]></ru>
	</translation>

	<translation>
		<nerd>Scheduled task job type</nerd>
		<ru><![CDATA[Тип задачи планировщика]]></ru>
	</translation>

	<translation>
		<nerd>Stop scheduler?</nerd>
		<ru><![CDATA[Остановить планировщик?]]></ru>
	</translation>

	<translation>
		<nerd>Create new scheduler task</nerd>
		<ru><![CDATA[Создать новую задачу планировщика]]></ru>
	</translation>

	<translation>
		<nerd>Job type</nerd>
		<ru><![CDATA[Тип задачи]]></ru>
	</translation>

	<translation>
		<nerd>Activity stream clean-up</nerd>
		<ru><![CDATA[Очистка ленты событий]]></ru>
	</translation>

	<translation>
		<nerd>Scheduled task id</nerd>
		<ru><![CDATA[ID задачи планировщика]]></ru>
	</translation>

	<translation>
		<nerd>Favorite entries generation</nerd>
		<ru><![CDATA[Генерирование избранного контента]]></ru>
	</translation>

	<translation>
		<nerd>Job execution history clean-up</nerd>
		<ru><![CDATA[Очистка истории выполнения задач]]></ru>
	</translation>

	<translation>
		<nerd>Photo appraisal</nerd>
		<ru><![CDATA[Оценка работы]]></ru>
	</translation>

	<translation>
		<nerd>There are active jobs</nerd>
		<ru><![CDATA[Есть активные задачи]]></ru>
	</translation>

	<translation>
		<nerd>Show active jobs</nerd>
		<ru><![CDATA[Показать активные задачи]]></ru>
	</translation>

	<translation>
		<nerd>Chains</nerd>
		<ru><![CDATA[Комплексные задачи]]></ru>
	</translation>

	<translation>
		<nerd>Data generation / Import</nerd>
		<ru><![CDATA[Генерация / Импорт]]></ru>
	</translation>

	<translation>
		<nerd>Recalculation</nerd>
		<ru><![CDATA[Пересчет]]></ru>
	</translation>

	<translation>
		<nerd>Clean-up</nerd>
		<ru><![CDATA[Очистка]]></ru>
	</translation>

	<translation>
		<nerd>Photo actions</nerd>
		<ru><![CDATA[Действия с работами]]></ru>
	</translation>

	<translation>
		<nerd>User actions / Favorites</nerd>
		<ru><![CDATA[Юзеры / Избранное]]></ru>
	</translation>

	<translation>
		<nerd>All saved jobs</nerd>
		<ru><![CDATA[Сохраненные задачи]]></ru>
	</translation>

	<translation>
		<nerd>Job templates</nerd>
		<ru><![CDATA[Шаблоны задач]]></ru>
	</translation>

	<translation>
		<nerd>Active / Performed</nerd>
		<ru><![CDATA[Акт. / Выполн.]]></ru>
	</translation>

	<translation>
		<nerd>Show member activity stream</nerd>
		<ru><![CDATA[Показать ленту событий пользователя]]></ru>
	</translation>

	<translation>
		<nerd>Registered</nerd>
		<ru><![CDATA[Дата регистрации]]></ru>
	</translation>

	<translation>
		<nerd>Favorites</nerd>
		<ru><![CDATA[Избранные работы]]></ru>
	</translation>

	<translation>
		<nerd>author plural</nerd>
		<ru><![CDATA[Авторы]]></ru>
	</translation>

	<translation>
		<nerd>model plural</nerd>
		<ru><![CDATA[Модели]]></ru>
	</translation>

	<translation>
		<nerd>makeup master plural</nerd>
		<ru><![CDATA[Визажисты]]></ru>
	</translation>

	<translation>
		<nerd>Best photos of author plural</nerd>
		<ru><![CDATA[Лучшие работы авторов]]></ru>
	</translation>

	<translation>
		<nerd>Best photos of model plural</nerd>
		<ru><![CDATA[Лучшие работы моделей]]></ru>
	</translation>

	<translation>
		<nerd>Best photos of makeup master plural</nerd>
		<ru><![CDATA[Лучшие работы визажистов]]></ru>
	</translation>

	<translation>
		<nerd>the status in the club has been changed from $1 to $2</nerd>
		<ru><![CDATA[статус в клубе изменен с $1 на $2]]></ru>
	</translation>

	<translation>
		<nerd>candidate</nerd>
		<ru><![CDATA[кандидат]]></ru>
	</translation>

	<translation>
		<nerd>member</nerd>
		<ru><![CDATA[член клуба]]></ru>
	</translation>

	<translation>
		<nerd>Photos</nerd>
		<ru><![CDATA[Работы]]></ru>
	</translation>

	<translation>
		<nerd>photos from category '$1'</nerd>
		<ru><![CDATA[из раздела $1]]></ru>
	</translation>

	<translation>
		<nerd>photos of member $1</nerd>
		<ru><![CDATA[$1]]></ru>
	</translation>

	<translation>
		<nerd>The very best of $1</nerd>
		<ru><![CDATA[Лучшие работы $1]]></ru>
	</translation>

	<translation>
		<nerd>Translations have been reloaded</nerd>
		<ru><![CDATA[Переводы загружены заново]]></ru>
	</translation>

	<translation>
		<nerd>The best photos</nerd>
		<ru><![CDATA[Лучшие работы]]></ru>
	</translation>

	<translation>
		<nerd>File '$1' contains unknown photosight categoryId '$2'. Note: file deletion may solve the problem because the import will be done again</nerd>
		<ru><![CDATA[Файл '$1' содержит название рубрики фотосайта '$2' которая не может быть идентифицирована (отсутствует в захрдкоженных значениях рубрик фотосайта PhotosightCategory). Удаление папки пользователя может решить проблему т.к. в этом случае все фотографии будут импортированы заново]]></ru>
	</translation>

	<translation>
		<nerd>Job progress</nerd>
		<ru><![CDATA[Прогресс выполнения задачи]]></ru>
	</translation>

	<translation>
		<nerd>Membership</nerd>
		<ru><![CDATA[Тип членства]]></ru>
	</translation>

	<translation>
		<nerd>Import comments</nerd>
		<ru><![CDATA[Импортировать комментарии]]></ru>
	</translation>

	<translation>
		<nerd>Delay between requests</nerd>
		<ru><![CDATA[Задержка между запросами]]></ru>
	</translation>

	<translation>
		<nerd>Pages to process</nerd>
		<ru><![CDATA[Импортировать страниц]]></ru>
	</translation>

	<translation>
		<nerd>User name</nerd>
		<ru><![CDATA[Имя пользователя]]></ru>
	</translation>

	<translation>
		<nerd>Being imported user</nerd>
		<ru><![CDATA[Импортируемый пользователь]]></ru>
	</translation>

	<translation>
		<nerd>Female</nerd>
		<ru><![CDATA[Женский]]></ru>
	</translation>

	<translation>
		<nerd>Male</nerd>
		<ru><![CDATA[Мужской]]></ru>
	</translation>

	<translation>
		<nerd>female</nerd>
		<ru><![CDATA[женский]]></ru>
	</translation>

	<translation>
		<nerd>male</nerd>
		<ru><![CDATA[мужской]]></ru>
	</translation>

	<translation>
		<nerd>Process all pages</nerd>
		<ru><![CDATA[Все страницы]]></ru>
	</translation>

	<translation>
		<nerd>Start time</nerd>
		<ru><![CDATA[Время начала выполнения]]></ru>
	</translation>

	<translation>
		<nerd>Jobs is performed successfully</nerd>
		<ru><![CDATA[Задача выполнена успешно]]></ru>
	</translation>

	<translation>
		<nerd>Performed $1 from $2</nerd>
		<ru><![CDATA[Выполнено $1 из $2]]></ru>
	</translation>

	<translation>
		<nerd>Job parameters</nerd>
		<ru><![CDATA[Параметры задачи]]></ru>
	</translation>

	<translation>
		<nerd>Execution time</nerd>
		<ru><![CDATA[Время выполнения]]></ru>
	</translation>

	<translation>
		<nerd>No messages found</nerd>
		<ru><![CDATA[Записей в логе выполнения задачи нет]]></ru>
	</translation>

	<translation>
		<nerd>Execution log</nerd>
		<ru><![CDATA[Лог выполнения задачи]]></ru>
	</translation>

	<translation>
		<nerd>Photosight user ids</nerd>
		<ru><![CDATA[ID пользователей фотосайта]]></ru>
	</translation>

	<translation>
		<nerd>Stop the Job</nerd>
		<ru><![CDATA[Прервать выполнение задачи]]></ru>
	</translation>

	<!--<translation>
		<nerd></nerd>
		<ru><![CDATA[]]></ru>
	</translation>

	<translation>
		<nerd></nerd>
		<ru><![CDATA[]]></ru>
	</translation>

	<translation>
		<nerd></nerd>
		<ru><![CDATA[]]></ru>
	</translation>

	<translation>
		<nerd></nerd>
		<ru><![CDATA[]]></ru>
	</translation>

	<translation>
		<nerd></nerd>
		<ru><![CDATA[]]></ru>
	</translation>-->

</translations>